CHANGELOG.rst
CONTRIBUTING.rst
LICENSE
MANIFEST.in
README.rst
setup.cfg
setup.py
awsprocesscreds/__init__.py
awsprocesscreds/cache.py
awsprocesscreds/cli.py
awsprocesscreds/compat.py
awsprocesscreds/saml.py
mnawsprocesscreds.egg-info/PKG-INFO
mnawsprocesscreds.egg-info/SOURCES.txt
mnawsprocesscreds.egg-info/dependency_links.txt
mnawsprocesscreds.egg-info/entry_points.txt
mnawsprocesscreds.egg-info/requires.txt
mnawsprocesscreds.egg-info/top_level.txt
tests/functional/__init__.py
tests/functional/conftest.py
tests/functional/test_saml.py
tests/unit/__init__.py
tests/unit/test_cache.py
tests/unit/test_saml.py