Metadata-Version: 1.1
Name: mnawsprocesscreds
Version: 0.0.3
Summary: AWS Process Credential Providers.
Home-page: https://github.com/gbvanrenswoude/awsprocesscreds
Author: Amazon Web Services
Author-email: UNKNOWN
License: Apache License 2.0
Keywords: aws credentials
Platform: UNKNOWN
Classifier: Development Status :: 2 - Pre-Alpha
Classifier: Intended Audience :: Developers
Classifier: Intended Audience :: System Administrators
Classifier: Natural Language :: English
Classifier: License :: OSI Approved :: Apache Software License
Classifier: Programming Language :: Python
Classifier: Programming Language :: Python :: 2.7
Classifier: Programming Language :: Python :: 3
Classifier: Programming Language :: Python :: 3.3
Classifier: Programming Language :: Python :: 3.4
Classifier: Programming Language :: Python :: 3.5
Classifier: Programming Language :: Python :: 3.6
